djangoldp_exposition/__init__.py
djangoldp_exposition/admin.py
djangoldp_exposition/apps.py
djangoldp_exposition/djangoldp_urls.py
djangoldp_exposition/models.py
djangoldp_exposition/tests.py
djangoldp_exposition/views.py
djangoldp_exposition/migrations/0001_initial.py
djangoldp_exposition/migrations/0002_auto_20201103_1628.py
djangoldp_exposition/migrations/0003_auto_20201103_2220.py
djangoldp_exposition/migrations/0004_auto_20201103_2227.py
djangoldp_exposition/migrations/0005_expo_archived.py
djangoldp_exposition/migrations/0006_auto_20201105_1056.py
djangoldp_exposition/migrations/0007_materiel.py
djangoldp_exposition/migrations/0008_auto_20201105_1740.py
djangoldp_exposition/migrations/0009_auto_20201110_1041.py
djangoldp_exposition/migrations/0010_auto_20201110_1047.py
djangoldp_exposition/migrations/0011_auto_20201115_1751.py
djangoldp_exposition/migrations/0012_auto_20201118_1000.py
djangoldp_exposition/migrations/0013_auto_20201119_1121.py
djangoldp_exposition/migrations/0014_auto_20201119_1222.py
djangoldp_exposition/migrations/0015_auto_20201123_1700.py
djangoldp_exposition/migrations/0016_auto_20201126_1530.py
djangoldp_exposition/migrations/0017_auto_20201127_1218.py
djangoldp_exposition/migrations/0018_auto_20201202_1123.py
djangoldp_exposition/migrations/0019_auto_20210131_1610.py
djangoldp_exposition/migrations/0020_auto_20210315_1354.py
djangoldp_exposition/migrations/0021_auto_20211030_1641.py
djangoldp_exposition/migrations/__init__.py
djangoldp_exposition-0.0.2.dist-info/METADATA
djangoldp_exposition-0.0.2.dist-info/WHEEL
djangoldp_exposition-0.0.2.dist-info/top_level.txt
djangoldp_exposition-0.0.2.dist-info/RECORD
