Metadata-Version: 2.1
Name: djangoldp-exposition
Version: 0.0.2
Summary: UNKNOWN
Home-page: UNKNOWN
License: MIT
Platform: UNKNOWN
Classifier: Programming Language :: Python :: 3
Requires-Dist: djangoldp (>=1.0.0)
